Workbook

Sheet Leia_me
A1: Central de Gestão da Loja – Planilha base (v0.4)
A2: Esta planilha NÃO contém dados reais da loja. Todo valor em azul/amarelo deve ser preenchido por você com dados do Painel do Mercado Livre.
A4: LEGENDA DE CORES
A5: Texto azul = valor digitado por você (entrada). Texto preto = fórmula (não editar).
A6: Fundo amarelo = célula que você precisa preencher ou revisar.
A8: ABAS
A9: Parametros – regras da loja (imposto 4%, margem mínima 15%, ACOS máx. 8%, meta R$ 5.000, custos fixos). Ajuste aqui, não nas fórmulas.
A10: Custos_SKU – uma linha por anúncio/canal: margem de contribuição, ACOS de equilíbrio, preço mínimo e status. A linha 6 é um EXEMPLO ILUSTRATIVO: apague-a e use suas linhas.
A11: Ads – dados do Mercado Ads exportados do Painel; calcula ACOS, ROAS, CPC, CTR, conversão e compara com o teto do SKU.
A12: Estoque – estoque próprio compartilhado (ML Coleta + Shopee) separado do Full; cobertura e ponto de reposição (sem ERP, esta é a fonte única).
A13: Fluxo_Caixa – boletos de compra (30 dias) x entradas do ML mês a mês: mostra se o lucro virou caixa.
A14: Resultado – lucro líquido mensal e acumulado contra a meta.
... A25: Parametros (revisar) → Custos_SKU → Ads → Estoque → Resultado (um mês por vez).

Sheet Parametros
A1: Parâmetros da loja
A3: Parâmetro | B3: Valor | C3: Origem / observação
A4: Imposto (Simples Nacional) – alíquota efetiva | B4: 0.04 | C4: Informado pelo proprietário. Confirmar com contador.
A5: Margem de contribuição mínima por produto | B5: 0.15 | C5: Informado pelo proprietário.
A6: ACOS máximo | B6: 0.08 | C6: Informado pelo proprietário.
A7: Meta de lucro líquido (R$) | B7: 5000 | C7: Informado. Meta de trabalho, revisar após a 1ª auditoria.
A8: Prazo da meta (meses) | B8: 3 | C8: Informado (90 dias).
A9: Contabilidade (fixo/mês) | B9: 300 | C9: Informado pelo proprietário.
A10: Outros custos fixos/mês | B10: 0 | C10: A PREENCHER: sistemas, transporte ao ponto de coleta, etc.
A11: Total de custos fixos/mês | B11: =B9+B10 -> 300 | C11: Fórmula.
A12: Embalagem por pedido (R$) | B12: =100/35 -> 2.8571429 | C12: R$ 100 em 35 pedidos, informado. Atualizar se mudar.
A13: Provisão de devoluções (% do preço) | B13: 0 | C13: A PREENCHER com histórico real. Zero = não considerada.
A14: Ticket médio atual | B14: 105 | C14: Informado.
A15: Pedidos por mês (atual) | B15: 35 | C15: Informado.
A16: Capital disponível para novo estoque | B16: 500 | C16: Informado. Sem aporte adicional.
A17: Prazo médio de reposição (dias) | B17: 25 | C17: Informado.
A18: Orçamento diário de Ads | B18: 50 | C18: Informado (orçamento máximo, não gasto real).
A19: Estoque de segurança (dias) | B19: 10 | C19: HIPÓTESE – ajustar conforme variação real da demanda.
A20: Prazo de pagamento ao fornecedor (dias) | B20: 30 | C20: Informado: compra a prazo, boleto de 30 dias.
A21: Limite de crédito com o fornecedor (R$) | B21: 0 | C21: A PREENCHER: quanto o fornecedor permite comprar a prazo. Zero = desconhecido.
A22: Prazo de liberação dos valores pelo ML (dias) | B22: 0 | C22: A PREENCHER com o prazo real do seu Painel (não presumido).
A23: Tarifa fixa por unidade (R$) para preço abaixo do limite | B23: 6.5 | C23: HIPÓTESE NÃO CONFIRMADA: blogs de terceiros citam R$ 6,25–6,75 (ponto médio) e, desde 02/03/2026, valor variável por peso/dimensão (~R$ 6–7 típico). Confirmar no simulador oficial do ML.
A24: Preço abaixo do qual a tarifa fixa se aplica (R$) | B24: 79 | C24: HIPÓTESE NÃO CONFIRMADA: fontes de terceiros citam R$ 79. Conferir no Painel.

Sheet Custos_SKU
A1: Custos e margem por SKU / canal
A2: Preencha as colunas A–M (azul). As demais são fórmulas. Linha 6 = EXEMPLO ILUSTRATIVO com valores fictícios: apague antes de usar.
A5: SKU | B5: ID do anúncio | C5: Título | D5: Canal | E5: Preço de venda (R$) | F5: Custo de compra (R$) | G5: Comissão ML (% do preço) | H5: Tarifa fixa ML (R$/un) | I5: Frete pago pelo vendedor (R$/un) | J5: Embalagem (R$/un) | K5: Devoluções (% do preço) | L5: Publicidade por unidade (R$) | M5: Origem do dado | N5: Imposto (R$) | O5: Margem de contribuição ANTES do Ads (R$) | P5: Margem antes do Ads (%) = ACOS de equilíbrio | Q5: Teto de ACOS p/ este SKU | R5: Margem de contribuição APÓS Ads (R$) | S5: Margem após Ads (%) | T5: Preço mínimo p/ margem mínima (R$) | U5: Status
A6: EXEMPLO-001 | B6: MLB0000000000 | C6: Exemplo ilustrativo (apagar) | D6: Full | E6: 100 | F6: 40 | G6: 0.14 | H6: =IF(E6="","",IF(E6<Parametros!$B$24,Parametros!$B$23,0)) -> 0 | I6: 0 | J6: =Parametros!$B$12 -> 2.8571429 | K6: =Parametros!$B$13 -> 0 | L6: 3 | M6: Hipótese | N6: =IF($E6="","",E6*Parametros!$B$4) -> 4 | O6: =IF($E6="","",E6-F6-E6*G6-H6-I6-J6-E6*K6-N6) -> 39.142857 | P6: =IF($E6="","",O6/E6) -> 0.39142857 | Q6: =IF($E6="","",MAX(0,MIN(P6,Parametros!$B$6))) -> 0.08 | R6: =IF($E6="","",O6-L6) -> 36.142857 | S6: =IF($E6="","",R6/E6) -> 0.36142857 | T6: =IF($E6="","",IF(1-G6-Parametros!$B$4-K6-Parametros!$B$5>0,(F6+H6+I6+J6+L6)/(1-G6-Parametros!$B$4-K6-Parametros!$B$5),"inviável")) -> 68.443497 | U6: =IF($E6="","",IF(S6>=Parametros!$B$5,"OK",IF(R6>0,"Abaixo da margem mínima","PREJUÍZO"))) -> OK
H7: =IF(E7="","",IF(E7<Parametros!$B$24,Parametros!$B$23,0)) | J7: =Parametros!$B$12 -> 2.8571429 | K7: =Parametros!$B$13 -> 0 | N7: =IF($E7="","",E7*Parametros!$B$4) | O7: =IF($E7="","",E7-F7-E7*G7-H7-I7-J7-E7*K7-N7) | P7: =IF($E7="","",O7/E7) | Q7: =IF($E7="","",MAX(0,MIN(P7,Parametros!$B$6))) | R7: =IF($E7="","",O7-L7) | S7: =IF($E7="","",R7/E7) | T7: =IF($E7="","",IF(1-G7-Parametros!$B$4-K7-Parametros!$B$5>0,(F7+H7+I7+J7+L7)/(1-G7-Parametros!$B$4-K7-Parametros!$B$5),"inviável")) | U7: =IF($E7="","",IF(S7>=Parametros!$B$5,"OK",IF(R7>0,"Abaixo da margem mínima","PREJUÍZO")))
H8: =IF(E8="","",IF(E8<Parametros!$B$24,Parametros!$B$23,0)) | J8: =Parametros!$B$12 -> 2.8571429 | K8: =Parametros!$B$13 -> 0 | N8: =IF($E8="","",E8*Parametros!$B$4) | O8: =IF($E8="","",E8-F8-E8*G8-H8-I8-J8-E8*K8-N8) | P8: =IF($E8="","",O8/E8) | Q8: =IF($E8="","",MAX(0,MIN(P8,Parametros!$B$6))) | R8: =IF($E8="","",O8-L8) | S8: =IF($E8="","",R8/E8) | T8: =IF($E8="","",IF(1-G8-Parametros!$B$4-K8-Parametros!$B$5>0,(F8+H8+I8+J8+L8)/(1-G8-Parametros!$B$4-K8-Parametros!$B$5),"inviável")) | U8: =IF($E8="","",IF(S8>=Parametros!$B$5,"OK",IF(R8>0,"Abaixo da margem mínima","PREJUÍZO")))
H9: =IF(E9="","",IF(E9<Parametros!$B$24,Parametros!$B$23,0)) | J9: =Parametros!$B$12 -> 2.8571429 | K9: =Parametros!$B$13 -> 0 | N9: =IF($E9="","",E9*Parametros!$B$4) | O9: =IF($E9="","",E9-F9-E9*G9-H9-I9-J9-E9*K9-N9) | P9: =IF($E9="","",O9/E9) | Q9: =IF($E9="","",MAX(0,MIN(P9,Parametros!$B$6))) | R9: =IF($E9="","",O9-L9) | S9: =IF($E9="","",R9/E9) | T9: =IF($E9="","",IF(1-G9-Parametros!$B$4-K9-Parametros!$B$5>0,(F9+H9+I9+J9+L9)/(1-G9-Parametros!$B$4-K9-Parametros!$B$5),"inviável")) | U9: =IF($E9="","",IF(S9>=Parametros!$B$5,"OK",IF(R9>0,"Abaixo da margem mínima","PREJUÍZO")))
H10: =IF(E10="","",IF(E10<Parametros!$B$24,Parametros!$B$23,0)) | J10: =Parametros!$B$12 -> 2.8571429 | K10: =Parametros!$B$13 -> 0 | N10: =IF($E10="","",E10*Parametros!$B$4) | O10: =IF($E10="","",E10-F10-E10*G10-H10-I10-J10-E10*K10-N10) | P10: =IF($E10="","",O10/E10) | Q10: =IF($E10="","",MAX(0,MIN(P10,Parametros!$B$6))) | R10: =IF($E10="","",O10-L10) | S10: =IF($E10="","",R10/E10) | T10: =IF($E10="","",IF(1-G10-Parametros!$B$4-K10-Parametros!$B$5>0,(F10+H10+I10+J10+L10)/(1-G10-Parametros!$B$4-K10-Parametros!$B$5),"inviável")) | U10: =IF($E10="","",IF(S10>=Parametros!$B$5,"OK",IF(R10>0,"Abaixo da margem mínima","PREJUÍZO")))
H11: =IF(E11="","",IF(E11<Parametros!$B$24,Parametros!$B$23,0)) | J11: =Parametros!$B$12 -> 2.8571429 | K11: =Parametros!$B$13 -> 0 | N11: =IF($E11="","",E11*Parametros!$B$4) | O11: =IF($E11="","",E11-F11-E11*G11-H11-I11-J11-E11*K11-N11) | P11: =IF($E11="","",O11/E11) | Q11: =IF($E11="","",MAX(0,MIN(P11,Parametros!$B$6))) | R11: =IF($E11="","",O11-L11) | S11: =IF($E11="","",R11/E11) | T11: =IF($E11="","",IF(1-G11-Parametros!$B$4-K11-Parametros!$B$5>0,(F11+H11+I11+J11+L11)/(1-G11-Parametros!$B$4-K11-Parametros!$B$5),"inviável")) | U11: =IF($E11="","",IF(S11>=Parametros!$B$5,"OK",IF(R11>0,"Abaixo da margem mínima","PREJUÍZO")))
H12: =IF(E12="","",IF(E12<Parametros!$B$24,Parametros!$B$23,0)) | J12: =Parametros!$B$12 -> 2.8571429 | K12: =Parametros!$B$13 -> 0 | N12: =IF($E12="","",E12*Parametros!$B$4) | O12: =IF($E12="","",E12-F12-E12*G12-H12-I12-J12-E12*K12-N12) | P12: =IF($E12="","",O12/E12) | Q12: =IF($E12="","",MAX(0,MIN(P12,Parametros!$B$6))) | R12: =IF($E12="","",O12-L12) | S12: =IF($E12="","",R12/E12) | T12: =IF($E12="","",IF(1-G12-Parametros!$B$4-K12-Parametros!$B$5>0,(F12+H12+I12+J12+L12)/(1-G12-Parametros!$B$4-K12-Parametros!$B$5),"inviável")) | U12: =IF($E12="","",IF(S12>=Parametros!$B$5,"OK",IF(R12>0,"Abaixo da margem mínima","PREJUÍZO")))
H13: =IF(E13="","",IF(E13<Parametros!$B$24,Parametros!$B$23,0)) | J13: =Parametros!$B$12 -> 2.8571429 | K13: =Parametros!$B$13 -> 0 | N13: =IF($E13="","",E13*Parametros!$B$4) | O13: =IF($E13="","",E13-F13-E13*G13-H13-I13-J13-E13*K13-N13) | P13: =IF($E13="","",O13/E13) | Q13: =IF($E13="","",MAX(0,MIN(P13,Parametros!$B$6))) | R13: =IF($E13="","",O13-L13) | S13: =IF($E13="","",R13/E13) | T13: =IF($E13="","",IF(1-G13-Parametros!$B$4-K13-Parametros!$B$5>0,(F13+H13+I13+J13+L13)/(1-G13-Parametros!$B$4-K13-Parametros!$B$5),"inviável")) | U13: =IF($E13="","",IF(S13>=Parametros!$B$5,"OK",IF(R13>0,"Abaixo da margem mínima","PREJUÍZO")))
H14: =IF(E14="","",IF(E14<Parametros!$B$24,Parametros!$B$23,0)) | J14: =Parametros!$B$12 -> 2.8571429 | K14: =Parametros!$B$13 -> 0 | N14: =IF($E14="","",E14*Parametros!$B$4) | O14: =IF($E14="","",E14-F14-E14*G14-H14-I14-J14-E14*K14-N14) | P14: =IF($E14="","",O14/E14) | Q14: =IF($E14="","",MAX(0,MIN(P14,Parametros!$B$6))) | R14: =IF($E14="","",O14-L14) | S14: =IF($E14="","",R14/E14) | T14: =IF($E14="","",IF(1-G14-Parametros!$B$4-K14-Parametros!$B$5>0,(F14+H14+I14+J14+L14)/(1-G14-Parametros!$B$4-K14-Parametros!$B$5),"inviável")) | U14: =IF($E14="","",IF(S14>=Parametros!$B$5,"OK",IF(R14>0,"Abaixo da margem mínima","PREJUÍZO")))
H15: =IF(E15="","",IF(E15<Parametros!$B$24,Parametros!$B$23,0)) | J15: =Parametros!$B$12 -> 2.8571429 | K15: =Parametros!$B$13 -> 0 | N15: =IF($E15="","",E15*Parametros!$B$4) | O15: =IF($E15="","",E15-F15-E15*G15-H15-I15-J15-E15*K15-N15) | P15: =IF($E15="","",O15/E15) | Q15: =IF($E15="","",MAX(0,MIN(P15,Parametros!$B$6))) | R15: =IF($E15="","",O15-L15) | S15: =IF($E15="","",R15/E15) | T15: =IF($E15="","",IF(1-G15-Parametros!$B$4-K15-Parametros!$B$5>0,(F15+H15+I15+J15+L15)/(1-G15-Parametros!$B$4-K15-Parametros!$B$5),"inviável")) | U15: =IF($E15="","",IF(S15>=Parametros!$B$5,"OK",IF(R15>0,"Abaixo da margem mínima","PREJUÍZO")))
H16: =IF(E16="","",IF(E16<Parametros!$B$24,Parametros!$B$23,0)) | J16: =Parametros!$B$12 -> 2.8571429 | K16: =Parametros!$B$13 -> 0 | N16: =IF($E16="","",E16*Parametros!$B$4) | O16: =IF($E16="","",E16-F16-E16*G16-H16-I16-J16-E16*K16-N16) | P16: =IF($E16="","",O16/E16) | Q16: =IF($E16="","",MAX(0,MIN(P16,Parametros!$B$6))) | R16: =IF($E16="","",O16-L16) | S16: =IF($E16="","",R16/E16) | T16: =IF($E16="","",IF(1-G16-Parametros!$B$4-K16-Parametros!$B$5>0,(F16+H16+I16+J16+L16)/(1-G16-Parametros!$B$4-K16-Parametros!$B$5),"inviável")) | U16: =IF($E16="","",IF(S16>=Parametros!$B$5,"OK",IF(R16>0,"Abaixo da margem mínima","PREJUÍZO")))
H17: =IF(E17="","",IF(E17<Parametros!$B$24,Parametros!$B$23,0)) | J17: =Parametros!$B$12 -> 2.8571429 | K17: =Parametros!$B$13 -> 0 | N17: =IF($E17="","",E17*Parametros!$B$4) | O17: =IF($E17="","",E17-F17-E17*G17-H17-I17-J17-E17*K17-N17) | P17: =IF($E17="","",O17/E17) | Q17: =IF($E17="","",MAX(0,MIN(P17,Parametros!$B$6))) | R17: =IF($E17="","",O17-L17) | S17: =IF($E17="","",R17/E17) | T17: =IF($E17="","",IF(1-G17-Parametros!$B$4-K17-Parametros!$B$5>0,(F17+H17+I17+J17+L17)/(1-G17-Parametros!$B$4-K17-Parametros!$B$5),"inviável")) | U17: =IF($E17="","",IF(S17>=Parametros!$B$5,"OK",IF(R17>0,"Abaixo da margem mínima","PREJUÍZO")))
H18: =IF(E18="","",IF(E18<Parametros!$B$24,Parametros!$B$23,0)) | J18: =Parametros!$B$12 -> 2.8571429 | K18: =Parametros!$B$13 -> 0 | N18: =IF($E18="","",E18*Parametros!$B$4) | O18: =IF($E18="","",E18-F18-E18*G18-H18-I18-J18-E18*K18-N18) | P18: =IF($E18="","",O18/E18) | Q18: =IF($E18="","",MAX(0,MIN(P18,Parametros!$B$6))) | R18: =IF($E18="","",O18-L18) | S18: =IF($E18="","",R18/E18) | T18: =IF($E18="","",IF(1-G18-Parametros!$B$4-K18-Parametros!$B$5>0,(F18+H18+I18+J18+L18)/(1-G18-Parametros!$B$4-K18-Parametros!$B$5),"inviável")) | U18: =IF($E18="","",IF(S18>=Parametros!$B$5,"OK",IF(R18>0,"Abaixo da margem mínima","PREJUÍZO")))
... H35: =IF(E35="","",IF(E35<Parametros!$B$24,Parametros!$B$23,0)) | J35: =Parametros!$B$12 -> 2.8571429 | K35: =Parametros!$B$13 -> 0 | N35: =IF($E35="","",E35*Parametros!$B$4) | O35: =IF($E35="","",E35-F35-E35*G35-H35-I35-J35-E35*K35-N35) | P35: =IF($E35="","",O35/E35) | Q35: =IF($E35="","",MAX(0,MIN(P35,Parametros!$B$6))) | R35: =IF($E35="","",O35-L35) | S35: =IF($E35="","",R35/E35) | T35: =IF($E35="","",IF(1-G35-Parametros!$B$4-K35-Parametros!$B$5>0,(F35+H35+I35+J35+L35)/(1-G35-Parametros!$B$4-K35-Parametros!$B$5),"inviável")) | U35: =IF($E35="","",IF(S35>=Parametros!$B$5,"OK",IF(R35>0,"Abaixo da margem mínima","PREJUÍZO")))

Sheet Ads
A1: Mercado Ads – desempenho
A2: Cole/preencha os dados exportados do Painel (azul). ACOS = gasto ÷ vendas atribuídas. Vendas atribuídas não são vendas incrementais. Linha 6 = EXEMPLO ILUSTRATIVO (apagar).
A5: Período | B5: Campanha | C5: SKU (igual à aba Custos_SKU) | D5: Impressões | E5: Cliques | F5: Gasto (R$) | G5: Vendas atribuídas (R$) | H5: Pedidos atribuídos | I5: CTR | J5: CPC (R$) | K5: Conversão | L5: ACOS | M5: ROAS | N5: Teto de ACOS do SKU | O5: Avaliação | P5: Canal
A6: Exemplo | B6: Campanha exemplo | C6: EXEMPLO-001 | D6: 10000 | E6: 100 | F6: 20 | G6: 400 | H6: 4 | I6: =IF(D6>0,E6/D6,"") -> 0.01 | J6: =IF(E6>0,F6/E6,"") -> 0.2 | K6: =IF(E6>0,H6/E6,"") -> 0.04 | L6: =IF(G6>0,F6/G6,"") -> 0.05 | M6: =IF(F6>0,G6/F6,"") -> 20 | N6: =IFERROR(INDEX(Custos_SKU!$Q$6:$Q$35,MATCH($C6,Custos_SKU!$A$6:$A$35,0)),"") -> 0.08 | O6: =IF(F6="","",IF(AND(F6>0,G6=0),"Gasto sem venda",IF(OR(L6="",N6=""),"Sem teto/ACOS",IF(L6<=N6,"Dentro do teto","ACIMA do teto")))) -> Dentro do teto | P6: ML
I7: =IF(D7>0,E7/D7,"") | J7: =IF(E7>0,F7/E7,"") | K7: =IF(E7>0,H7/E7,"") | L7: =IF(G7>0,F7/G7,"") | M7: =IF(F7>0,G7/F7,"") | N7: =IFERROR(INDEX(Custos_SKU!$Q$6:$Q$35,MATCH($C7,Custos_SKU!$A$6:$A$35,0)),"") | O7: =IF(F7="","",IF(AND(F7>0,G7=0),"Gasto sem venda",IF(OR(L7="",N7=""),"Sem teto/ACOS",IF(L7<=N7,"Dentro do teto","ACIMA do teto"))))
I8: =IF(D8>0,E8/D8,"") | J8: =IF(E8>0,F8/E8,"") | K8: =IF(E8>0,H8/E8,"") | L8: =IF(G8>0,F8/G8,"") | M8: =IF(F8>0,G8/F8,"") | N8: =IFERROR(INDEX(Custos_SKU!$Q$6:$Q$35,MATCH($C8,Custos_SKU!$A$6:$A$35,0)),"") | O8: =IF(F8="","",IF(AND(F8>0,G8=0),"Gasto sem venda",IF(OR(L8="",N8=""),"Sem teto/ACOS",IF(L8<=N8,"Dentro do teto","ACIMA do teto"))))
I9: =IF(D9>0,E9/D9,"") | J9: =IF(E9>0,F9/E9,"") | K9: =IF(E9>0,H9/E9,"") | L9: =IF(G9>0,F9/G9,"") | M9: =IF(F9>0,G9/F9,"") | N9: =IFERROR(INDEX(Custos_SKU!$Q$6:$Q$35,MATCH($C9,Custos_SKU!$A$6:$A$35,0)),"") | O9: =IF(F9="","",IF(AND(F9>0,G9=0),"Gasto sem venda",IF(OR(L9="",N9=""),"Sem teto/ACOS",IF(L9<=N9,"Dentro do teto","ACIMA do teto"))))
I10: =IF(D10>0,E10/D10,"") | J10: =IF(E10>0,F10/E10,"") | K10: =IF(E10>0,H10/E10,"") | L10: =IF(G10>0,F10/G10,"") | M10: =IF(F10>0,G10/F10,"") | N10: =IFERROR(INDEX(Custos_SKU!$Q$6:$Q$35,MATCH($C10,Custos_SKU!$A$6:$A$35,0)),"") | O10: =IF(F10="","",IF(AND(F10>0,G10=0),"Gasto sem venda",IF(OR(L10="",N10=""),"Sem teto/ACOS",IF(L10<=N10,"Dentro do teto","ACIMA do teto"))))
I11: =IF(D11>0,E11/D11,"") | J11: =IF(E11>0,F11/E11,"") | K11: =IF(E11>0,H11/E11,"") | L11: =IF(G11>0,F11/G11,"") | M11: =IF(F11>0,G11/F11,"") | N11: =IFERROR(INDEX(Custos_SKU!$Q$6:$Q$35,MATCH($C11,Custos_SKU!$A$6:$A$35,0)),"") | O11: =IF(F11="","",IF(AND(F11>0,G11=0),"Gasto sem venda",IF(OR(L11="",N11=""),"Sem teto/ACOS",IF(L11<=N11,"Dentro do teto","ACIMA do teto"))))
I12: =IF(D12>0,E12/D12,"") | J12: =IF(E12>0,F12/E12,"") | K12: =IF(E12>0,H12/E12,"") | L12: =IF(G12>0,F12/G12,"") | M12: =IF(F12>0,G12/F12,"") | N12: =IFERROR(INDEX(Custos_SKU!$Q$6:$Q$35,MATCH($C12,Custos_SKU!$A$6:$A$35,0)),"") | O12: =IF(F12="","",IF(AND(F12>0,G12=0),"Gasto sem venda",IF(OR(L12="",N12=""),"Sem teto/ACOS",IF(L12<=N12,"Dentro do teto","ACIMA do teto"))))
I13: =IF(D13>0,E13/D13,"") | J13: =IF(E13>0,F13/E13,"") | K13: =IF(E13>0,H13/E13,"") | L13: =IF(G13>0,F13/G13,"") | M13: =IF(F13>0,G13/F13,"") | N13: =IFERROR(INDEX(Custos_SKU!$Q$6:$Q$35,MATCH($C13,Custos_SKU!$A$6:$A$35,0)),"") | O13: =IF(F13="","",IF(AND(F13>0,G13=0),"Gasto sem venda",IF(OR(L13="",N13=""),"Sem teto/ACOS",IF(L13<=N13,"Dentro do teto","ACIMA do teto"))))
I14: =IF(D14>0,E14/D14,"") | J14: =IF(E14>0,F14/E14,"") | K14: =IF(E14>0,H14/E14,"") | L14: =IF(G14>0,F14/G14,"") | M14: =IF(F14>0,G14/F14,"") | N14: =IFERROR(INDEX(Custos_SKU!$Q$6:$Q$35,MATCH($C14,Custos_SKU!$A$6:$A$35,0)),"") | O14: =IF(F14="","",IF(AND(F14>0,G14=0),"Gasto sem venda",IF(OR(L14="",N14=""),"Sem teto/ACOS",IF(L14<=N14,"Dentro do teto","ACIMA do teto"))))
I15: =IF(D15>0,E15/D15,"") | J15: =IF(E15>0,F15/E15,"") | K15: =IF(E15>0,H15/E15,"") | L15: =IF(G15>0,F15/G15,"") | M15: =IF(F15>0,G15/F15,"") | N15: =IFERROR(INDEX(Custos_SKU!$Q$6:$Q$35,MATCH($C15,Custos_SKU!$A$6:$A$35,0)),"") | O15: =IF(F15="","",IF(AND(F15>0,G15=0),"Gasto sem venda",IF(OR(L15="",N15=""),"Sem teto/ACOS",IF(L15<=N15,"Dentro do teto","ACIMA do teto"))))
I16: =IF(D16>0,E16/D16,"") | J16: =IF(E16>0,F16/E16,"") | K16: =IF(E16>0,H16/E16,"") | L16: =IF(G16>0,F16/G16,"") | M16: =IF(F16>0,G16/F16,"") | N16: =IFERROR(INDEX(Custos_SKU!$Q$6:$Q$35,MATCH($C16,Custos_SKU!$A$6:$A$35,0)),"") | O16: =IF(F16="","",IF(AND(F16>0,G16=0),"Gasto sem venda",IF(OR(L16="",N16=""),"Sem teto/ACOS",IF(L16<=N16,"Dentro do teto","ACIMA do teto"))))
I17: =IF(D17>0,E17/D17,"") | J17: =IF(E17>0,F17/E17,"") | K17: =IF(E17>0,H17/E17,"") | L17: =IF(G17>0,F17/G17,"") | M17: =IF(F17>0,G17/F17,"") | N17: =IFERROR(INDEX(Custos_SKU!$Q$6:$Q$35,MATCH($C17,Custos_SKU!$A$6:$A$35,0)),"") | O17: =IF(F17="","",IF(AND(F17>0,G17=0),"Gasto sem venda",IF(OR(L17="",N17=""),"Sem teto/ACOS",IF(L17<=N17,"Dentro do teto","ACIMA do teto"))))
I18: =IF(D18>0,E18/D18,"") | J18: =IF(E18>0,F18/E18,"") | K18: =IF(E18>0,H18/E18,"") | L18: =IF(G18>0,F18/G18,"") | M18: =IF(F18>0,G18/F18,"") | N18: =IFERROR(INDEX(Custos_SKU!$Q$6:$Q$35,MATCH($C18,Custos_SKU!$A$6:$A$35,0)),"") | O18: =IF(F18="","",IF(AND(F18>0,G18=0),"Gasto sem venda",IF(OR(L18="",N18=""),"Sem teto/ACOS",IF(L18<=N18,"Dentro do teto","ACIMA do teto"))))
... I35: =IF(D35>0,E35/D35,"") | J35: =IF(E35>0,F35/E35,"") | K35: =IF(E35>0,H35/E35,"") | L35: =IF(G35>0,F35/G35,"") | M35: =IF(F35>0,G35/F35,"") | N35: =IFERROR(INDEX(Custos_SKU!$Q$6:$Q$35,MATCH($C35,Custos_SKU!$A$6:$A$35,0)),"") | O35: =IF(F35="","",IF(AND(F35>0,G35=0),"Gasto sem venda",IF(OR(L35="",N35=""),"Sem teto/ACOS",IF(L35<=N35,"Dentro do teto","ACIMA do teto"))))
A36: TOTAL | D36: =SUM(D6:D35) -> 10000 | E36: =SUM(E6:E35) -> 100 | F36: =SUM(F6:F35) -> 20 | G36: =SUM(G6:G35) -> 400 | H36: =SUM(H6:H35) -> 4 | I36: =IF(D36>0,E36/D36,"") -> 0.01 | J36: =IF(E36>0,F36/E36,"") -> 0.2 | K36: =IF(E36>0,H36/E36,"") -> 0.04 | L36: =IF(G36>0,F36/G36,"") -> 0.05 | M36: =IF(F36>0,G36/F36,"") -> 20

Sheet Estoque
A1: Estoque e reposição (estoque próprio compartilhado: ML Coleta + Shopee)
A2: Fonte única de estoque (sem ERP). Atualize a cada venda nos dois canais para evitar venda sem estoque. O estoque no Full é do ML e não atende a Shopee. Linha 6 = EXEMPLO ILUSTRATIVO (apagar).
A5: SKU | B5: Estoque próprio (un) – ML Coleta + Shopee | C5: Estoque no Full (un) – só ML | D5: Vendas 30 dias – ML Full (un) | E5: Vendas 30 dias – ML Coleta (un) | F5: Vendas 30 dias – Shopee (un) | G5: Giro diário próprio (un/dia) | H5: Giro diário Full (un/dia) | I5: Cobertura estoque próprio (dias) | J5: Cobertura Full (dias) | K5: Ponto de reposição próprio (un) | L5: Custo unitário (R$) | M5: Capital p/ repor 30 dias (R$) | N5: Status | O5: Data da contagem
A6: EXEMPLO-001 | B6: 30 | C6: 10 | D6: 10 | E6: 15 | F6: 15 | G6: =IF(A6="","",(E6+F6)/30) -> 1 | H6: =IF(A6="","",D6/30) -> 0.33333333 | I6: =IF(A6="","",IF(G6>0,B6/G6,"")) -> 30 | J6: =IF(A6="","",IF(H6>0,C6/H6,"")) -> 30 | K6: =IF(A6="","",G6*(Parametros!$B$17+Parametros!$B$19)) -> 35 | L6: 40 | M6: =IF(A6="","",(G6+H6)*30*L6) -> 1600 | N6: =IF(A6="","",IF(OR(AND(G6>0,B6<=0),AND(H6>0,C6<=0)),"RUPTURA",IF(OR(AND(G6>0,B6<=K6),AND(H6>0,C6<=H6*(Parametros!$B$17+Parametros!$B$19))),"REPOR (abaixo do ponto)",IF(G6+H6=0,"Sem giro: revisar",IF(OR(AND(G6>0,I6>120),AND(H6>0,J6>120)),"Excesso (>120 dias)","OK"))))) -> REPOR (abaixo do ponto)
G7: =IF(A7="","",(E7+F7)/30) | H7: =IF(A7="","",D7/30) | I7: =IF(A7="","",IF(G7>0,B7/G7,"")) | J7: =IF(A7="","",IF(H7>0,C7/H7,"")) | K7: =IF(A7="","",G7*(Parametros!$B$17+Parametros!$B$19)) | M7: =IF(A7="","",(G7+H7)*30*L7) | N7: =IF(A7="","",IF(OR(AND(G7>0,B7<=0),AND(H7>0,C7<=0)),"RUPTURA",IF(OR(AND(G7>0,B7<=K7),AND(H7>0,C7<=H7*(Parametros!$B$17+Parametros!$B$19))),"REPOR (abaixo do ponto)",IF(G7+H7=0,"Sem giro: revisar",IF(OR(AND(G7>0,I7>120),AND(H7>0,J7>120)),"Excesso (>120 dias)","OK")))))
G8: =IF(A8="","",(E8+F8)/30) | H8: =IF(A8="","",D8/30) | I8: =IF(A8="","",IF(G8>0,B8/G8,"")) | J8: =IF(A8="","",IF(H8>0,C8/H8,"")) | K8: =IF(A8="","",G8*(Parametros!$B$17+Parametros!$B$19)) | M8: =IF(A8="","",(G8+H8)*30*L8) | N8: =IF(A8="","",IF(OR(AND(G8>0,B8<=0),AND(H8>0,C8<=0)),"RUPTURA",IF(OR(AND(G8>0,B8<=K8),AND(H8>0,C8<=H8*(Parametros!$B$17+Parametros!$B$19))),"REPOR (abaixo do ponto)",IF(G8+H8=0,"Sem giro: revisar",IF(OR(AND(G8>0,I8>120),AND(H8>0,J8>120)),"Excesso (>120 dias)","OK")))))
G9: =IF(A9="","",(E9+F9)/30) | H9: =IF(A9="","",D9/30) | I9: =IF(A9="","",IF(G9>0,B9/G9,"")) | J9: =IF(A9="","",IF(H9>0,C9/H9,"")) | K9: =IF(A9="","",G9*(Parametros!$B$17+Parametros!$B$19)) | M9: =IF(A9="","",(G9+H9)*30*L9) | N9: =IF(A9="","",IF(OR(AND(G9>0,B9<=0),AND(H9>0,C9<=0)),"RUPTURA",IF(OR(AND(G9>0,B9<=K9),AND(H9>0,C9<=H9*(Parametros!$B$17+Parametros!$B$19))),"REPOR (abaixo do ponto)",IF(G9+H9=0,"Sem giro: revisar",IF(OR(AND(G9>0,I9>120),AND(H9>0,J9>120)),"Excesso (>120 dias)","OK")))))
G10: =IF(A10="","",(E10+F10)/30) | H10: =IF(A10="","",D10/30) | I10: =IF(A10="","",IF(G10>0,B10/G10,"")) | J10: =IF(A10="","",IF(H10>0,C10/H10,"")) | K10: =IF(A10="","",G10*(Parametros!$B$17+Parametros!$B$19)) | M10: =IF(A10="","",(G10+H10)*30*L10) | N10: =IF(A10="","",IF(OR(AND(G10>0,B10<=0),AND(H10>0,C10<=0)),"RUPTURA",IF(OR(AND(G10>0,B10<=K10),AND(H10>0,C10<=H10*(Parametros!$B$17+Parametros!$B$19))),"REPOR (abaixo do ponto)",IF(G10+H10=0,"Sem giro: revisar",IF(OR(AND(G10>0,I10>120),AND(H10>0,J10>120)),"Excesso (>120 dias)","OK")))))
G11: =IF(A11="","",(E11+F11)/30) | H11: =IF(A11="","",D11/30) | I11: =IF(A11="","",IF(G11>0,B11/G11,"")) | J11: =IF(A11="","",IF(H11>0,C11/H11,"")) | K11: =IF(A11="","",G11*(Parametros!$B$17+Parametros!$B$19)) | M11: =IF(A11="","",(G11+H11)*30*L11) | N11: =IF(A11="","",IF(OR(AND(G11>0,B11<=0),AND(H11>0,C11<=0)),"RUPTURA",IF(OR(AND(G11>0,B11<=K11),AND(H11>0,C11<=H11*(Parametros!$B$17+Parametros!$B$19))),"REPOR (abaixo do ponto)",IF(G11+H11=0,"Sem giro: revisar",IF(OR(AND(G11>0,I11>120),AND(H11>0,J11>120)),"Excesso (>120 dias)","OK")))))
G12: =IF(A12="","",(E12+F12)/30) | H12: =IF(A12="","",D12/30) | I12: =IF(A12="","",IF(G12>0,B12/G12,"")) | J12: =IF(A12="","",IF(H12>0,C12/H12,"")) | K12: =IF(A12="","",G12*(Parametros!$B$17+Parametros!$B$19)) | M12: =IF(A12="","",(G12+H12)*30*L12) | N12: =IF(A12="","",IF(OR(AND(G12>0,B12<=0),AND(H12>0,C12<=0)),"RUPTURA",IF(OR(AND(G12>0,B12<=K12),AND(H12>0,C12<=H12*(Parametros!$B$17+Parametros!$B$19))),"REPOR (abaixo do ponto)",IF(G12+H12=0,"Sem giro: revisar",IF(OR(AND(G12>0,I12>120),AND(H12>0,J12>120)),"Excesso (>120 dias)","OK")))))
G13: =IF(A13="","",(E13+F13)/30) | H13: =IF(A13="","",D13/30) | I13: =IF(A13="","",IF(G13>0,B13/G13,"")) | J13: =IF(A13="","",IF(H13>0,C13/H13,"")) | K13: =IF(A13="","",G13*(Parametros!$B$17+Parametros!$B$19)) | M13: =IF(A13="","",(G13+H13)*30*L13) | N13: =IF(A13="","",IF(OR(AND(G13>0,B13<=0),AND(H13>0,C13<=0)),"RUPTURA",IF(OR(AND(G13>0,B13<=K13),AND(H13>0,C13<=H13*(Parametros!$B$17+Parametros!$B$19))),"REPOR (abaixo do ponto)",IF(G13+H13=0,"Sem giro: revisar",IF(OR(AND(G13>0,I13>120),AND(H13>0,J13>120)),"Excesso (>120 dias)","OK")))))
G14: =IF(A14="","",(E14+F14)/30) | H14: =IF(A14="","",D14/30) | I14: =IF(A14="","",IF(G14>0,B14/G14,"")) | J14: =IF(A14="","",IF(H14>0,C14/H14,"")) | K14: =IF(A14="","",G14*(Parametros!$B$17+Parametros!$B$19)) | M14: =IF(A14="","",(G14+H14)*30*L14) | N14: =IF(A14="","",IF(OR(AND(G14>0,B14<=0),AND(H14>0,C14<=0)),"RUPTURA",IF(OR(AND(G14>0,B14<=K14),AND(H14>0,C14<=H14*(Parametros!$B$17+Parametros!$B$19))),"REPOR (abaixo do ponto)",IF(G14+H14=0,"Sem giro: revisar",IF(OR(AND(G14>0,I14>120),AND(H14>0,J14>120)),"Excesso (>120 dias)","OK")))))
G15: =IF(A15="","",(E15+F15)/30) | H15: =IF(A15="","",D15/30) | I15: =IF(A15="","",IF(G15>0,B15/G15,"")) | J15: =IF(A15="","",IF(H15>0,C15/H15,"")) | K15: =IF(A15="","",G15*(Parametros!$B$17+Parametros!$B$19)) | M15: =IF(A15="","",(G15+H15)*30*L15) | N15: =IF(A15="","",IF(OR(AND(G15>0,B15<=0),AND(H15>0,C15<=0)),"RUPTURA",IF(OR(AND(G15>0,B15<=K15),AND(H15>0,C15<=H15*(Parametros!$B$17+Parametros!$B$19))),"REPOR (abaixo do ponto)",IF(G15+H15=0,"Sem giro: revisar",IF(OR(AND(G15>0,I15>120),AND(H15>0,J15>120)),"Excesso (>120 dias)","OK")))))
G16: =IF(A16="","",(E16+F16)/30) | H16: =IF(A16="","",D16/30) | I16: =IF(A16="","",IF(G16>0,B16/G16,"")) | J16: =IF(A16="","",IF(H16>0,C16/H16,"")) | K16: =IF(A16="","",G16*(Parametros!$B$17+Parametros!$B$19)) | M16: =IF(A16="","",(G16+H16)*30*L16) | N16: =IF(A16="","",IF(OR(AND(G16>0,B16<=0),AND(H16>0,C16<=0)),"RUPTURA",IF(OR(AND(G16>0,B16<=K16),AND(H16>0,C16<=H16*(Parametros!$B$17+Parametros!$B$19))),"REPOR (abaixo do ponto)",IF(G16+H16=0,"Sem giro: revisar",IF(OR(AND(G16>0,I16>120),AND(H16>0,J16>120)),"Excesso (>120 dias)","OK")))))
G17: =IF(A17="","",(E17+F17)/30) | H17: =IF(A17="","",D17/30) | I17: =IF(A17="","",IF(G17>0,B17/G17,"")) | J17: =IF(A17="","",IF(H17>0,C17/H17,"")) | K17: =IF(A17="","",G17*(Parametros!$B$17+Parametros!$B$19)) | M17: =IF(A17="","",(G17+H17)*30*L17) | N17: =IF(A17="","",IF(OR(AND(G17>0,B17<=0),AND(H17>0,C17<=0)),"RUPTURA",IF(OR(AND(G17>0,B17<=K17),AND(H17>0,C17<=H17*(Parametros!$B$17+Parametros!$B$19))),"REPOR (abaixo do ponto)",IF(G17+H17=0,"Sem giro: revisar",IF(OR(AND(G17>0,I17>120),AND(H17>0,J17>120)),"Excesso (>120 dias)","OK")))))
G18: =IF(A18="","",(E18+F18)/30) | H18: =IF(A18="","",D18/30) | I18: =IF(A18="","",IF(G18>0,B18/G18,"")) | J18: =IF(A18="","",IF(H18>0,C18/H18,"")) | K18: =IF(A18="","",G18*(Parametros!$B$17+Parametros!$B$19)) | M18: =IF(A18="","",(G18+H18)*30*L18) | N18: =IF(A18="","",IF(OR(AND(G18>0,B18<=0),AND(H18>0,C18<=0)),"RUPTURA",IF(OR(AND(G18>0,B18<=K18),AND(H18>0,C18<=H18*(Parametros!$B$17+Parametros!$B$19))),"REPOR (abaixo do ponto)",IF(G18+H18=0,"Sem giro: revisar",IF(OR(AND(G18>0,I18>120),AND(H18>0,J18>120)),"Excesso (>120 dias)","OK")))))
... G35: =IF(A35="","",(E35+F35)/30) | H35: =IF(A35="","",D35/30) | I35: =IF(A35="","",IF(G35>0,B35/G35,"")) | J35: =IF(A35="","",IF(H35>0,C35/H35,"")) | K35: =IF(A35="","",G35*(Parametros!$B$17+Parametros!$B$19)) | M35: =IF(A35="","",(G35+H35)*30*L35) | N35: =IF(A35="","",IF(OR(AND(G35>0,B35<=0),AND(H35>0,C35<=0)),"RUPTURA",IF(OR(AND(G35>0,B35<=K35),AND(H35>0,C35<=H35*(Parametros!$B$17+Parametros!$B$19))),"REPOR (abaixo do ponto)",IF(G35+H35=0,"Sem giro: revisar",IF(OR(AND(G35>0,I35>120),AND(H35>0,J35>120)),"Excesso (>120 dias)","OK")))))
A37: Capital total necessário para repor 30 dias: | M37: =SUM(M6:M35) -> 1600
A38: Capital próprio + crédito do fornecedor (Parametros): | M38: =Parametros!$B$16+Parametros!$B$21 -> 500
A39: Saldo (negativo = capital insuficiente): | M39: =M38-M37 -> -1100

Sheet Fluxo_Caixa
A1: Fluxo de caixa: boletos de compra x entradas
A2: Compras a prazo (boleto em 30 dias): a compra do mês M vence no mês M+1. O lucro só vira caixa se as entradas do ML cobrirem os boletos.
A3: Saldo inicial de caixa (R$): | B3: 0
A4: Item | B4: Mês 1 | C4: Mês 2 | D4: Mês 3 | E4: Mês 4
A5: (+) Entradas líquidas liberadas pelo ML (já sem tarifas, frete e Ads)
A6: (-) Boletos vencendo no mês | C6: =B12 -> 0 | D6: =C12 -> 0 | E6: =D12 -> 0
A7: (-) Impostos pagos
A8: (-) Custos fixos | B8: =Parametros!$B$11 -> 300 | C8: =Parametros!$B$11 -> 300 | D8: =Parametros!$B$11 -> 300 | E8: =Parametros!$B$11 -> 300
A9: (-) Embalagem paga
A10: (=) Caixa do mês | B10: =B5-SUM(B6:B9) -> -300 | C10: =C5-SUM(C6:C9) -> -300 | D10: =D5-SUM(D6:D9) -> -300 | E10: =E5-SUM(E6:E9) -> -300
A11: Caixa acumulado (inclui saldo inicial) | B11: =$B$3+B10 -> -300 | C11: =B11+C10 -> -600 | D11: =C11+D10 -> -900 | E11: =D11+E10 -> -1200
A12: Compras do mês (boletos gerados, vencem no mês seguinte)
A13: Dívida de fornecedor em aberto no fim do mês | B13: =B12 -> 0 | C13: =C12 -> 0 | D13: =D12 -> 0 | E13: =E12 -> 0
A14: Crédito de fornecedor ainda disponível | B14: =MAX(0,Parametros!$B$21-B13) -> 0 | C14: =MAX(0,Parametros!$B$21-C13) -> 0 | D14: =MAX(0,Parametros!$B$21-D13) -> 0 | E14: =MAX(0,Parametros!$B$21-E13) -> 0
A16: Mês 1: preencha em 'Boletos vencendo' os boletos de compras de antes do início do controle. Impostos e embalagem: valores efetivamente pagos no mês.
A17: Se 'Limite de crédito' em Parametros estiver zerado, a linha de crédito disponível não tem significado.

Sheet Resultado
A1: Lucro líquido mensal x meta
A2: Preencha as linhas azuis a cada mês com os valores reais do Painel e da contabilidade. Imposto e custos fixos vêm dos Parametros.
A4: Item | B4: Mês 1 | C4: Mês 2 | D4: Mês 3 | E4: Total
A5: Pedidos (un) | E5: =SUM(B5:D5) -> 0
A6: Faturamento bruto (R$) | E6: =SUM(B6:D6) -> 0
A7: (-) Custo dos produtos vendidos | E7: =SUM(B7:D7) -> 0
A8: (-) Comissões e tarifas do Mercado Livre | E8: =SUM(B8:D8) -> 0
A9: (-) Frete pago pelo vendedor | E9: =SUM(B9:D9) -> 0
A10: (-) Embalagem | E10: =SUM(B10:D10) -> 0
A11: (-) Devoluções e reembolsos | E11: =SUM(B11:D11) -> 0
A12: (-) Imposto (Simples) | B12: =B6*Parametros!$B$4 -> 0 | C12: =C6*Parametros!$B$4 -> 0 | D12: =D6*Parametros!$B$4 -> 0 | E12: =SUM(B12:D12) -> 0
A13: (-) Publicidade (gasto total com Ads) | E13: =SUM(B13:D13) -> 0
A14: (=) Margem de contribuição | B14: =B6-SUM(B7:B13) -> 0 | C14: =C6-SUM(C7:C13) -> 0 | D14: =D6-SUM(D7:D13) -> 0 | E14: =SUM(B14:D14) -> 0
A15: Margem de contribuição (% do faturamento) | B15: =IF(B6>0,B14/B6,"") | C15: =IF(C6>0,C14/C6,"") | D15: =IF(D6>0,D14/D6,"") | E15: =IF(E6>0,E14/E6,"")
A16: (-) Custos fixos | B16: =Parametros!$B$11 -> 300 | C16: =Parametros!$B$11 -> 300 | D16: =Parametros!$B$11 -> 300 | E16: =SUM(B16:D16) -> 900
A17: (=) LUCRO LÍQUIDO DO MÊS | B17: =B14-B16 -> -300 | C17: =C14-C16 -> -300 | D17: =D14-D16 -> -300 | E17: =SUM(B17:D17) -> -900
A18: Lucro líquido acumulado | B18: =SUM($B17:B17) -> -300 | C18: =SUM($B17:C17) -> -600 | D18: =SUM($B17:D17) -> -900 | E18: =E17 -> -900
A19: Falta para a meta | B19: =Parametros!$B$7-B18 -> 5300 | C19: =Parametros!$B$7-C18 -> 5600 | D19: =Parametros!$B$7-D18 -> 5900 | E19: =Parametros!$B$7-E17 -> 5900
A20: % da meta atingido | B20: =IF(Parametros!$B$7>0,B18/Parametros!$B$7,"") -> -0.06 | C20: =IF(Parametros!$B$7>0,C18/Parametros!$B$7,"") -> -0.12 | D20: =IF(Parametros!$B$7>0,D18/Parametros!$B$7,"") -> -0.18 | E20: =IF(Parametros!$B$7>0,E17/Parametros!$B$7,"") -> -0.18
A21: Ticket médio (R$) | B21: =IF(B5>0,B6/B5,"") | C21: =IF(C5>0,C6/C5,"") | D21: =IF(D5>0,D6/D5,"") | E21: =IF(E5>0,E6/E5,"")
A22: Gasto com Ads ÷ faturamento total | B22: =IF(B6>0,B13/B6,"") | C22: =IF(C6>0,C13/C6,"") | D22: =IF(D6>0,D13/D6,"") | E22: =IF(E6>0,E13/E6,"")
A24: Atenção: meta = lucro contábil (receita menos todos os custos). Reposição de estoque não é descontada aqui; acompanhe o caixa separadamente.
A26: Faturamento por canal (informativo)
A27: Faturamento Mercado Livre (R$) | E27: =SUM(B27:D27) -> 0
A28: Faturamento Shopee (R$) | E28: =SUM(B28:D28) -> 0
A29: Diferença vs. faturamento bruto acima (deve ser zero) | B29: =B6-B27-B28 -> 0 | C29: =C6-C27-C28 -> 0 | D29: =D6-D27-D28 -> 0 | E29: =E6-E27-E28 -> 0

Sheet Simulador
A1: Simulador: pedidos necessários para a meta
A2: Aritmética sobre os Parametros. Não é previsão. m = margem de contribuição depois de todos os custos variáveis (incluindo Ads e embalagem).
A4: Lucro líquido mensal necessário (constante) | B4: =Parametros!$B$7/Parametros!$B$8 -> 1666.6667
A5: Custos fixos/mês | B5: =Parametros!$B$11 -> 300
A6: Contribuição necessária/mês | B6: =B4+B5 -> 1966.6667
A7: Lucro mensal necessário no último mês (rampa linear a partir de zero) | B7: =2*Parametros!$B$7/(Parametros!$B$8+1) -> 2500
A8: Contribuição necessária no último mês (rampa) | B8: =B7+B5 -> 2800
A10: Cenário de margem m (editável) | B10: Faturamento/mês (ritmo constante) | C10: Pedidos/mês (ticket atual) | D10: x o ritmo atual | E10: Faturamento no último mês (rampa) | F10: Pedidos no último mês (rampa) | G10: x o ritmo atual (rampa)
A11: 0.15 | B11: =IF(A11>0,$B$6/A11,"") -> 13111.111 | C11: =IF(A11>0,B11/Parametros!$B$14,"") -> 124.86772 | D11: =IF(AND(A11>0,Parametros!$B$15>0),C11/Parametros!$B$15,"") -> 3.5676493 | E11: =IF(A11>0,$B$8/A11,"") -> 18666.667 | F11: =IF(A11>0,E11/Parametros!$B$14,"") -> 177.77778 | G11: =IF(AND(A11>0,Parametros!$B$15>0),F11/Parametros!$B$15,"") -> 5.0793651
A12: 0.1 | B12: =IF(A12>0,$B$6/A12,"") -> 19666.667 | C12: =IF(A12>0,B12/Parametros!$B$14,"") -> 187.30159 | D12: =IF(AND(A12>0,Parametros!$B$15>0),C12/Parametros!$B$15,"") -> 5.3514739 | E12: =IF(A12>0,$B$8/A12,"") -> 28000 | F12: =IF(A12>0,E12/Parametros!$B$14,"") -> 266.66667 | G12: =IF(AND(A12>0,Parametros!$B$15>0),F12/Parametros!$B$15,"") -> 7.6190476
A13: 0.07 | B13: =IF(A13>0,$B$6/A13,"") -> 28095.238 | C13: =IF(A13>0,B13/Parametros!$B$14,"") -> 267.5737 | D13: =IF(AND(A13>0,Parametros!$B$15>0),C13/Parametros!$B$15,"") -> 7.6449627 | E13: =IF(A13>0,$B$8/A13,"") -> 40000 | F13: =IF(A13>0,E13/Parametros!$B$14,"") -> 380.95238 | G13: =IF(AND(A13>0,Parametros!$B$15>0),F13/Parametros!$B$15,"") -> 10.884354
A15: Referência: 7% ≈ margem mínima 15% menos ACOS máx. 8% (pior caso, se o Ads atribuir todas as vendas).
